<?xml version="1.0" encoding="utf-8"?>
<dict name="Our bathroom"><words><word name="bathrobe" translation="peignoir de bain" png="bathrobe.svg" sound="232. lamp.wav"/><word name="bathtub" translation="baignoire" png="bathtub.svg" sound="232. lamp.wav"/><word name="comb" translation="peigne" png="comb.svg" sound=". lamp.wav"/><word name="shampoo" translation="shampooing" png="shampoo.svg" sound=". lamp.wav"/><word name="shower" translation="douche" png="shower.svg" sound=". lamp.wav"/><word name="slippers" translation="chaussons" png="slippers.svg" sound=". lamp.wav"/><word name="soap" translation="savon" png="soap.svg" sound=". lamp.wav"/><word name="sponge" translation="éponge" png="sponge.svg" sound=". lamp.wav"/><word name="toilet" translation="toilette" png="toilet.svg" sound=". lamp.wav"/><word name="toilet paper" translation="papier de toilette" png="toilet_paper.svg" sound=". lamp.wav"/><word name="toothbrush" translation="brosse à dents" png="toothbrush.svg" sound=". lamp.wav"/><word name="toothpaste" translation="dentifrice" png="toothpaste.svg" sound=". lamp.wav"/><word name="towel" translation="serviette" png="towel.svg" sound=". lamp.wav"/><word name="washbasin" translation="lavabo" png="washbasin.svg" sound=". lamp.wav"/></words></dict>