<?xml version="1.0" encoding="utf-8"?>
<dicts><dict locked="1" title="過去現在と未来" name="過去現在と未来" png="sceptre.svg" zipFile="past_present_and_future"/><dict locked="1" title="アート" name="アート" png="violin.svg" zipFile="art"/><dict locked="1" title="国と人" name="国と人" png="Bulgaria.svg" zipFile="countries_and_people"/><dict locked="1" title="休日" name="休日" png="balloons.svg" zipFile="holidays"/><dict locked="1" title="自然と環境" name="自然と環境" png="soil_pollution.svg" zipFile="nature_and_environment"/><dict locked="1" title="時間や天候" name="時間や天候" png="weather_forecast.svg" zipFile="time_the_weather"/><dict locked="1" title="農場" name="農場" png="combine_harvester.svg" zipFile="the_farm"/><dict locked="1" title="動物園で" name="動物園で" png="elephant.svg" zipFile="at_the_zoo"/><dict locked="1" title="スポーツ" name="スポーツ" png="the_Olympic_flame.svg" zipFile="sport"/><dict locked="1" title="海岸に" name="海岸に" png="sand_castle.svg" zipFile="at_the_seaside"/><dict locked="1" title="動き" name="動き" png="ride_a_bike.svg" zipFile="movement"/><dict locked="1" title="私たちのバスルーム" name="私たちのバスルーム" png="bathtub.svg" zipFile="our_bathroom"/><dict locked="1" title="色" name="色" png="purple.svg" zipFile="colours"/><dict locked="1" title="数字" name="数字" png="seven.svg" zipFile="numbers"/><dict locked="1" title="フォーム" name="フォーム" png="circle.svg" zipFile="shapes"/><dict locked="1" title="私たちの台所" name="私たちの台所" png="stove.svg" zipFile="our_kitchen"/><dict locked="1" title="職業" name="職業" png="computer_programmer.svg" zipFile="professions"/><dict locked="1" title="病院で" name="病院で" png="hospital.svg" zipFile="at_the_hospital"/><dict locked="1" title="反対" name="反対" png="up_down.svg" zipFile="opposites"/><dict locked="1" title="旅行やT" name="旅行やT" png="bus_station.svg" zipFile="travel_and_transport"/><dict locked="1" title="私の学校" name="私の学校" png="alphabet.svg" zipFile="my_school"/><dict locked="1" title="食べ物や飲み物" name="食べ物や飲み物" png="pizza.svg" zipFile="food_and_drink"/><dict locked="1" title="市場に" name="市場に" png="watermelon.svg" zipFile="at_the_market"/><dict locked="1" title="私の町" name="私の町" png="bench.svg" zipFile="my_town"/><dict locked="0" title="私たちの居間" name="私たちの居間" png="sofa.svg" zipFile="our_living_room"/><dict locked="1" title="私の家族" name="私の家族" png="we.svg" zipFile="my_family"/><dict locked="1" title="私たちの回廊" name="私たちの回廊" png="coat_rack.svg" zipFile="our_corridor"/><dict locked="0" title="自宅での活動" name="自宅での活動" png="hoover2.svg" zipFile="activities_at_home"/><dict locked="1" title="自分の部屋" name="自分の部屋" png="bedside table.svg" zipFile="my_room"/><dict locked="1" title="ショッピングモールで" name="ショッピングモールで" png="shopping_cart.svg" zipFile="at_the_shopping_mall"/></dicts>