<dict name="At a Seaside">
    <words>
        <word name="air mattress" translation="надуваем дюшек" png="air_mattress.svg" sound="232. lamp.wav"/>
        <word name="anchor" translation="котва" png="anchor.svg" sound="232. lamp.wav"/>
        <word name="beach" translation="плаж" png="beach.svg" sound="232. lamp.wav"/>
        <word name="binoculars" translation="бинокъл" png="binoculars.svg" sound="232. lamp.wav"/>
        <word name="boat" translation="лодка" png="boat.svg" sound="232. lamp.wav"/>
        <word name="buoy" translation="шамандура" png="buoy.svg" sound="232. lamp.wav"/>
        <word name="crab" translation="рак" png="crab.svg" sound="232. lamp.wav"/>
        <word name="crane" translation="кран" png="crane.svg" sound="232. lamp.wav"/>
        <word name="deskchair" translation="шезлонг" png="desk_chair.svg" sound="232. lamp.wav"/>
        <word name="flag" translation="флаг" png="flag.svg" sound="232. lamp.wav"/>
        <word name="flip-flops" translation="джапанки" png="flip_flops.svg" sound="232. lamp.wav"/>
        <word name="island" translation="остров" png="island.svg" sound="232. lamp.wav"/>
        <word name="Jet Ski" translation="джет" png="jet.svg" sound="232. lamp.wav"/>
        <word name="lifeguard" translation="спасител" png="lifeguard.svg" sound="232. lamp.wav"/>
        <word name="lighthouse" translation="фар" png="lighthouse.svg" sound="232. lamp.wav"/>
        <word name="mask" translation="маска" png="mask.svg" sound="232. lamp.wav"/>
        <word name="motorboat" translation="катер" png="motor_boat.svg" sound="232. lamp.wav"/>
        <word name="mussel" translation="мида" png="mussel.svg" sound="232. lamp.wav"/>
        <word name="pebbles" translation="камъчета" png="pebbles.svg" sound="232. lamp.wav"/>
        <word name="pedfal boat" translation="водно колело" png="pedfal_boat.svg" sound="232. lamp.wav"/>
        <word name="rake" translation="гребло" png="rake.svg" sound="232. lamp.wav"/>
        <word name="rope" translation="въже" png="rope.svg" sound="232. lamp.wav"/>
        <word name="life belt" translation="спасителна жилетка" png="safety_belt.svg" sound="232. lamp.wav"/>
        <word name="life jacket" translation="спасителна жилетка" png="safety_jacket.svg" sound="232. lamp.wav"/>
        <word name="sailing ship" translation="платноход" png="sailing_ship.svg" sound="232. lamp.wav"/>
        <word name="sand" translation="пясък" png="sand.svg" sound="232. lamp.wav"/>
        <word name="sand castle" translation="пясъчен замък" png="sand_castle.svg" sound="232. lamp.wav"/>
        <word name="scuba diver" translation="водолаз" png="scuba_diver.svg" sound="232. lamp.wav"/>
        <word name="sea" translation="море" png="sea.svg" sound="232. lamp.wav"/>
        <word name="seagull" translation="чайка" png="seagull.svg" sound="232. lamp.wav"/>
        <word name="seaweed" translation="водорасли" png="seaweed.svg" sound="232. lamp.wav"/>
        <word name="shell" translation="раковина" png="shells.svg" sound="232. lamp.wav"/>
        <word name="ship" translation="кораб" png="ship.svg" sound="232. lamp.wav"/>
        <word name="shovel" translation="лопатка" png="shovel.svg" sound="232. lamp.wav"/>
        <word name="snorkel" translation="шнорхел" png="snorkel.svg" sound="232. lamp.wav"/>
        <word name="sunglasses" translation="слънчви очила" png="sunglasses.svg" sound="232. lamp.wav"/>
        <word name="sun hat" translation="сламена шапка" png="sunhat.svg" sound="232. lamp.wav"/>
        <word name="sunscreen" translation="слинцезащитен крем" png="sunscreen.svg" sound="232. lamp.wav"/>
        <word name="flippers" translation="плавници" png="swim_fins.svg" sound="232. lamp.wav"/>
        <word name="swimming ring" translation="пояс" png="swimming_belt.svg" sound="232. lamp.wav"/>
        <word name="umbrella" translation="чадър" png="umbrella.svg" sound="232. lamp.wav"/>
        <word name="waterskiing" translation="водни ски" png="waterskiing.svg" sound="232. lamp.wav"/>
        <word name="waves" translation="вълни" png="waves.svg" sound="232. lamp.wav"/>
        <word name="windsurf" translation="уиндсърф" png="windsurf.svg" sound="232. lamp.wav"/>
        <word name="yacht" translation="яхта" png="yacht.svg" sound="232. lamp.wav"/>
    </words>
</dict>